pfund_terminal/__init__.py
pfund_terminal-0.0.1.dev1.dist-info/LICENSE
pfund_terminal-0.0.1.dev1.dist-info/METADATA
pfund_terminal-0.0.1.dev1.dist-info/WHEEL
pfund_terminal-0.0.1.dev1.dist-info/entry_points.txt
pfund_terminal-0.0.1.dev1.dist-info/RECORD
