Metadata-Version: 2.1
Name: pfund-terminal
Version: 0.0.1.dev1
Summary: A free alternative to the Bloomberg Terminal.
Home-page: https://pfund.ai
License: Apache-2.0
Keywords: terminal,bloomberg,financial,data,market,data science,finance,investing,trading
Author: stephenyau
Author-email: softwareentrepreneer+pfund-terminal@gmail.com
Requires-Python: >=3.10,<4.0
Classifier: Intended Audience :: Developers
Classifier: Intended Audience :: Financial and Insurance Industry
Classifier: Intended Audience :: Information Technology
Classifier: Intended Audience :: Science/Research
Classifier: License :: OSI Approved :: Apache Software License
Classifier: Operating System :: OS Independent
Classifier: Programming Language :: Python :: 3
Classifier: Programming Language :: Python :: 3.10
Classifier: Programming Language :: Python :: 3.11
Classifier: Programming Language :: Python :: 3.12
Classifier: Programming Language :: Python :: 3.13
Classifier: Topic :: Office/Business :: Financial :: Investment
Classifier: Topic :: Scientific/Engineering :: Information Analysis
Classifier: Topic :: Software Development :: Libraries
Requires-Dist: marimo (>=0.9.10,<0.10.0)
Requires-Dist: notebook (>=7.2.2,<8.0.0)
Requires-Dist: pfeed[all] (>=0.0.2,<0.0.3)
Requires-Dist: pfolio[all] (>=0.0.2,<0.0.3)
Requires-Dist: pfund-plot[all] (>=0.0.1.dev2,<0.0.2)
Requires-Dist: pfund[all] (>=0.0.2,<0.0.3)
Requires-Dist: rich (>=13.9.2,<14.0.0)
Requires-Dist: textual (>=0.83.0,<0.84.0)
Requires-Dist: xonsh[full] (>=0.18.3,<0.19.0)
Project-URL: Documentation, https://pfund-terminal-docs.pfund.ai
Project-URL: Repository, https://github.com/PFund-Software-Ltd/pfund-terminal
